py2sterimol/__init__.py
py2sterimol/py2sterimol.py
test/__init__.py
test/test_py2sterimol.py
py2sterimol-0.0.0.dist-info/LICENSE
py2sterimol-0.0.0.dist-info/METADATA
py2sterimol-0.0.0.dist-info/WHEEL
py2sterimol-0.0.0.dist-info/top_level.txt
py2sterimol-0.0.0.dist-info/RECORD
