Metadata-Version: 2.1
Name: py2sterimol
Version: 0.0.0
Summary: Thin client Python interface to the original Fortran implementation of Sterimol parameters.
Home-page: https://github.com/JacksonBurns/py2sterimol
Author: Jackson Burns
License: MIT
Classifier: Programming Language :: Python :: 3
License-File: LICENSE
